{"commitInfo":{"timestamp":1776643647739,"operation":"WRITE","operationParameters":{"mode":"Overwrite","partitionBy":"[]"},"readVersion":8,"isolationLevel":"Serializable","isBlindAppend":false,"operationMetrics":{"numFiles":"1","numOutputRows":"10","numOutputBytes":"1506"},"engineInfo":"Apache-Spark/3.4.1 Delta-Lake/2.4.0","txnId":"49f8635d-92ce-4a68-8420-dfdf66f81182"}}
{"add":{"path":"part-00000-9a158e41-916b-45e1-ab1e-8d4b08b14925-c000.snappy.parquet","partitionValues":{},"size":1506,"modificationTime":1776643647685,"dataChange":true,"stats":"{\"numRecords\":10,\"minValues\":{\"trending_region\":\"AU\",\"time_bucket\":\"2026-04-20T05:30:00.000+05:30\",\"total_views\":2277254796,\"avg_engagement_rate\":0.035194729565093036},\"maxValues\":{\"trending_region\":\"US\",\"time_bucket\":\"2026-04-20T05:35:00.000+05:30\",\"total_views\":6249801200,\"avg_engagement_rate\":0.05073332526068693},\"nullCount\":{\"trending_region\":0,\"time_bucket\":0,\"total_views\":0,\"avg_engagement_rate\":0}}"}}
{"remove":{"path":"part-00000-86d49344-9777-4395-bf93-bb157c3dd3dc-c000.snappy.parquet","deletionTimestamp":1776643647739,"dataChange":true,"extendedFileMetadata":true,"partitionValues":{},"size":1503}}
