{"commitInfo":{"timestamp":1777501118078,"operation":"WRITE","operationParameters":{"mode":"Overwrite","partitionBy":"[]"},"readVersion":61,"isolationLevel":"Serializable","isBlindAppend":false,"operationMetrics":{"numFiles":"1","numOutputRows":"202","numOutputBytes":"9594"},"engineInfo":"Apache-Spark/3.4.1 Delta-Lake/2.4.0","txnId":"7cb74ee2-099c-48ad-b491-5144b9a45933"}}
{"add":{"path":"part-00000-e94f0bac-22bc-4827-b036-4d3ab8b75fe3-c000.snappy.parquet","partitionValues":{},"size":9594,"modificationTime":1777501118007,"dataChange":true,"stats":"{\"numRecords\":202,\"minValues\":{\"trending_region\":\"AU\",\"category_name\":\"Autos & Vehicles\",\"duration_bucket\":\"Long\",\"video_count\":1,\"avg_views_in_bucket\":0.0,\"avg_er_in_bucket\":0.0,\"sum_views_in_bucket\":0,\"sum_engagements_in_bucket\":1873},\"maxValues\":{\"trending_region\":\"US\",\"category_name\":\"Travel & Events\",\"duration_bucket\":\"Short\",\"video_count\":544,\"avg_views_in_bucket\":2.252311963852814E7,\"avg_er_in_bucket\":0.16837091057609077,\"sum_views_in_bucket\":296299000862,\"sum_engagements_in_bucket\":12439291303},\"nullCount\":{\"trending_region\":0,\"category_name\":0,\"duration_bucket\":0,\"video_count\":0,\"avg_views_in_bucket\":0,\"avg_er_in_bucket\":0,\"sum_views_in_bucket\":0,\"sum_engagements_in_bucket\":0}}"}}
{"remove":{"path":"part-00000-aed235ce-304c-4ba3-b499-8f7b9b0ce115-c000.snappy.parquet","deletionTimestamp":1777501118078,"dataChange":true,"extendedFileMetadata":true,"partitionValues":{},"size":9601}}
