{"commitInfo":{"timestamp":1777461969795,"operation":"WRITE","operationParameters":{"mode":"Overwrite","partitionBy":"[]"},"readVersion":26,"isolationLevel":"Serializable","isBlindAppend":false,"operationMetrics":{"numFiles":"1","numOutputRows":"201","numOutputBytes":"9562"},"engineInfo":"Apache-Spark/3.4.1 Delta-Lake/2.4.0","txnId":"f39e6e32-319b-40f5-b56a-1d499dc911c7"}}
{"add":{"path":"part-00000-47b408f9-ca8d-46e9-8452-d5c332bdd235-c000.snappy.parquet","partitionValues":{},"size":9562,"modificationTime":1777461969726,"dataChange":true,"stats":"{\"numRecords\":201,\"minValues\":{\"trending_region\":\"AU\",\"category_name\":\"Autos & Vehicles\",\"duration_bucket\":\"Long\",\"video_count\":1,\"avg_views_in_bucket\":40540.41333333333,\"avg_er_in_bucket\":0.008887399806444663,\"sum_views_in_bucket\":118052,\"sum_engagements_in_bucket\":3929},\"maxValues\":{\"trending_region\":\"US\",\"category_name\":\"Travel & Events\",\"duration_bucket\":\"Short\",\"video_count\":530,\"avg_views_in_bucket\":2.252311963852814E7,\"avg_er_in_bucket\":0.17531227417812717,\"sum_views_in_bucket\":280410932606,\"sum_engagements_in_bucket\":11736478015},\"nullCount\":{\"trending_region\":0,\"category_name\":0,\"duration_bucket\":0,\"video_count\":0,\"avg_views_in_bucket\":0,\"avg_er_in_bucket\":0,\"sum_views_in_bucket\":0,\"sum_engagements_in_bucket\":0}}"}}
{"remove":{"path":"part-00000-5ae99a41-2462-4708-8e9b-5f20898934e0-c000.snappy.parquet","deletionTimestamp":1777461969795,"dataChange":true,"extendedFileMetadata":true,"partitionValues":{},"size":9562}}
