{"commitInfo":{"timestamp":1777547212436,"operation":"WRITE","operationParameters":{"mode":"Overwrite","partitionBy":"[]"},"readVersion":14,"isolationLevel":"Serializable","isBlindAppend":false,"operationMetrics":{"numFiles":"1","numOutputRows":"119","numOutputBytes":"3392"},"engineInfo":"Apache-Spark/3.4.1 Delta-Lake/2.4.0","txnId":"f8bb536d-91ce-44e7-be4e-82b58234b4ab"}}
{"add":{"path":"part-00000-b891c301-9b0c-44f9-a768-b2857219ce0b-c000.snappy.parquet","partitionValues":{},"size":3392,"modificationTime":1777547212310,"dataChange":true,"stats":"{\"numRecords\":119,\"minValues\":{\"trending_region\":\"AU\",\"time_bucket\":\"2026-04-30T13:40:00.000+05:30\",\"total_views\":14779237,\"avg_engagement_rate\":0.020788916951736475},\"maxValues\":{\"trending_region\":\"US\",\"time_bucket\":\"2026-04-30T16:35:00.000+05:30\",\"total_views\":7259298541,\"avg_engagement_rate\":0.05878918908291985},\"nullCount\":{\"trending_region\":0,\"time_bucket\":0,\"total_views\":0,\"avg_engagement_rate\":0}}"}}
{"remove":{"path":"part-00000-80c94754-ec56-4f3e-96ed-ef7064c31f03-c000.snappy.parquet","deletionTimestamp":1777547212436,"dataChange":true,"extendedFileMetadata":true,"partitionValues":{},"size":3375}}
