{"commitInfo":{"timestamp":1777414801309,"operation":"WRITE","operationParameters":{"mode":"Overwrite","partitionBy":"[]"},"readVersion":116,"isolationLevel":"Serializable","isBlindAppend":false,"operationMetrics":{"numFiles":"1","numOutputRows":"3050","numOutputBytes":"115397"},"engineInfo":"Apache-Spark/3.4.1 Delta-Lake/2.4.0","txnId":"6c38395d-3bb2-4574-9c99-05d6bd24fc6b"}}
{"add":{"path":"part-00000-cc827dfd-68a6-4a8c-946c-b0fe5d634b61-c000.snappy.parquet","partitionValues":{},"size":115397,"modificationTime":1777414801212,"dataChange":true,"stats":"{\"numRecords\":3050,\"minValues\":{\"channel_title\":\" Goal Machine\",\"videos\":1,\"total_views\":15617,\"total_engagements\":0,\"avg_engagement_rate\":0.0,\"avg_subscribers\":0.0},\"maxValues\":{\"channel_title\":\"💖 Jenna With The Pink 💖\",\"videos\":21,\"total_views\":844026550,\"total_engagements\":45714426,\"avg_engagement_rate\":0.2645150095436405,\"avg_subscribers\":4.79E8},\"nullCount\":{\"channel_title\":0,\"videos\":0,\"total_views\":0,\"total_engagements\":0,\"avg_engagement_rate\":0,\"avg_subscribers\":0}}"}}
{"remove":{"path":"part-00000-0405aa3f-4a1e-4a34-97c9-c3f0469f0780-c000.snappy.parquet","deletionTimestamp":1777414801309,"dataChange":true,"extendedFileMetadata":true,"partitionValues":{},"size":115396}}
