{"commitInfo":{"timestamp":1777500740162,"operation":"WRITE","operationParameters":{"mode":"Overwrite","partitionBy":"[]"},"readVersion":252,"isolationLevel":"Serializable","isBlindAppend":false,"operationMetrics":{"numFiles":"1","numOutputRows":"7948","numOutputBytes":"108809"},"engineInfo":"Apache-Spark/3.4.1 Delta-Lake/2.4.0","txnId":"bbbc8669-7bcd-409c-a6d4-8161d67eab2b"}}
{"add":{"path":"part-00000-43dfb8e0-0945-4499-a3b0-2f9702d13bbf-c000.snappy.parquet","partitionValues":{},"size":108809,"modificationTime":1777500739731,"dataChange":true,"stats":"{\"numRecords\":7948,\"minValues\":{\"category_name\":\"Autos & Vehicles\",\"time_bucket\":\"2026-04-15T10:40:00.000+05:30\",\"total_views\":0,\"total_engagements\":1123,\"trending_region\":\"AU\"},\"maxValues\":{\"category_name\":\"Travel & Events\",\"time_bucket\":\"2026-04-30T03:35:00.000+05:30\",\"total_views\":4278097601,\"total_engagements\":179671862,\"trending_region\":\"US\"},\"nullCount\":{\"category_name\":0,\"time_bucket\":0,\"total_views\":0,\"total_engagements\":0,\"trending_region\":0}}"}}
{"remove":{"path":"part-00000-cd4b0d03-dfee-4766-a637-b8339447efc7-c000.snappy.parquet","deletionTimestamp":1777500740161,"dataChange":true,"extendedFileMetadata":true,"partitionValues":{},"size":106919}}
