{"commitInfo":{"timestamp":1777420501675,"operation":"WRITE","operationParameters":{"mode":"Overwrite","partitionBy":"[]"},"readVersion":134,"isolationLevel":"Serializable","isBlindAppend":false,"operationMetrics":{"numFiles":"1","numOutputRows":"1291","numOutputBytes":"19655"},"engineInfo":"Apache-Spark/3.4.1 Delta-Lake/2.4.0","txnId":"f1db55f0-df1b-4a0b-b92a-822dad40546b"}}
{"add":{"path":"part-00000-39dc00bf-5f01-4bc2-b43a-23690b2b6977-c000.snappy.parquet","partitionValues":{},"size":19655,"modificationTime":1777420501604,"dataChange":true,"stats":"{\"numRecords\":1291,\"minValues\":{\"category_name\":\"Autos & Vehicles\",\"time_bucket\":\"2026-04-15T10:40:00.000+05:30\",\"total_views\":35351,\"total_engagements\":2367},\"maxValues\":{\"category_name\":\"Travel & Events\",\"time_bucket\":\"2026-04-29T05:20:00.000+05:30\",\"total_views\":17409286006,\"total_engagements\":723325327},\"nullCount\":{\"category_name\":0,\"time_bucket\":0,\"total_views\":0,\"total_engagements\":0}}"}}
{"remove":{"path":"part-00000-134189cc-7530-4c9c-b3f2-d469820575e3-c000.snappy.parquet","deletionTimestamp":1777420501675,"dataChange":true,"extendedFileMetadata":true,"partitionValues":{},"size":19646}}
