{"commitInfo":{"timestamp":1777460396223,"operation":"WRITE","operationParameters":{"mode":"Overwrite","partitionBy":"[]"},"readVersion":199,"isolationLevel":"Serializable","isBlindAppend":false,"operationMetrics":{"numFiles":"1","numOutputRows":"7107","numOutputBytes":"97458"},"engineInfo":"Apache-Spark/3.4.1 Delta-Lake/2.4.0","txnId":"c6115b64-4e60-41e8-bcda-6d526906a82b"}}
{"add":{"path":"part-00000-f14c9f67-c2ed-44b2-a169-a7c4939fa768-c000.snappy.parquet","partitionValues":{},"size":97458,"modificationTime":1777460396134,"dataChange":true,"stats":"{\"numRecords\":7107,\"minValues\":{\"category_name\":\"Autos & Vehicles\",\"time_bucket\":\"2026-04-15T10:40:00.000+05:30\",\"total_views\":35351,\"total_engagements\":2367,\"trending_region\":\"AU\"},\"maxValues\":{\"category_name\":\"Travel & Events\",\"time_bucket\":\"2026-04-29T16:25:00.000+05:30\",\"total_views\":4278097601,\"total_engagements\":179671862,\"trending_region\":\"US\"},\"nullCount\":{\"category_name\":0,\"time_bucket\":0,\"total_views\":0,\"total_engagements\":0,\"trending_region\":0}}"}}
{"remove":{"path":"part-00000-32921161-abd6-4639-97a3-866f3de880e7-c000.snappy.parquet","deletionTimestamp":1777460396223,"dataChange":true,"extendedFileMetadata":true,"partitionValues":{},"size":97458}}
