{"commitInfo":{"timestamp":1777236343969,"operation":"WRITE","operationParameters":{"mode":"Overwrite","partitionBy":"[]"},"readVersion":54,"isolationLevel":"Serializable","isBlindAppend":false,"operationMetrics":{"numFiles":"1","numOutputRows":"1109","numOutputBytes":"17036"},"engineInfo":"Apache-Spark/3.4.1 Delta-Lake/2.4.0","txnId":"9ed409b2-020b-415b-aab5-1e7b22065e0d"}}
{"add":{"path":"part-00000-eab36aaa-8aa1-4d42-9d5d-74795fa31da5-c000.snappy.parquet","partitionValues":{},"size":17036,"modificationTime":1777236343898,"dataChange":true,"stats":"{\"numRecords\":1109,\"minValues\":{\"category_name\":\"Autos & Vehicles\",\"time_bucket\":\"2026-04-15T10:40:00.000+05:30\",\"total_views\":35351,\"total_engagements\":2367},\"maxValues\":{\"category_name\":\"Travel & Events\",\"time_bucket\":\"2026-04-27T02:10:00.000+05:30\",\"total_views\":17409286006,\"total_engagements\":723325327},\"nullCount\":{\"category_name\":0,\"time_bucket\":0,\"total_views\":0,\"total_engagements\":0}}"}}
{"remove":{"path":"part-00000-e4894d54-0414-43eb-8d68-8d2ec59cb751-c000.snappy.parquet","deletionTimestamp":1777236343969,"dataChange":true,"extendedFileMetadata":true,"partitionValues":{},"size":17027}}
