{"commitInfo":{"timestamp":1777421723024,"operation":"WRITE","operationParameters":{"mode":"Overwrite","partitionBy":"[]"},"readVersion":161,"isolationLevel":"Serializable","isBlindAppend":false,"operationMetrics":{"numFiles":"1","numOutputRows":"1333","numOutputBytes":"20260"},"engineInfo":"Apache-Spark/3.4.1 Delta-Lake/2.4.0","txnId":"2b82f41c-b1eb-4129-a35a-ea41a8bb7337"}}
{"add":{"path":"part-00000-776e9a12-dbe3-49d7-8206-ba3f3c0c3e62-c000.snappy.parquet","partitionValues":{},"size":20260,"modificationTime":1777421722980,"dataChange":true,"stats":"{\"numRecords\":1333,\"minValues\":{\"category_name\":\"Autos & Vehicles\",\"time_bucket\":\"2026-04-15T10:40:00.000+05:30\",\"total_views\":35351,\"total_engagements\":2367},\"maxValues\":{\"category_name\":\"Travel & Events\",\"time_bucket\":\"2026-04-29T05:40:00.000+05:30\",\"total_views\":17409286006,\"total_engagements\":723325327},\"nullCount\":{\"category_name\":0,\"time_bucket\":0,\"total_views\":0,\"total_engagements\":0}}"}}
{"remove":{"path":"part-00000-fc82f234-bd1f-4d1b-8169-39eeaaea19cb-c000.snappy.parquet","deletionTimestamp":1777421723024,"dataChange":true,"extendedFileMetadata":true,"partitionValues":{},"size":20260}}
