{"commitInfo":{"timestamp":1777463358083,"operation":"WRITE","operationParameters":{"mode":"Overwrite","partitionBy":"[]"},"readVersion":56,"isolationLevel":"Serializable","isBlindAppend":false,"operationMetrics":{"numFiles":"1","numOutputRows":"70","numOutputBytes":"2914"},"engineInfo":"Apache-Spark/3.4.1 Delta-Lake/2.4.0","txnId":"6aaf6202-4d77-474b-b567-901c22942956"}}
{"add":{"path":"part-00000-82551e27-70e6-4f84-95c8-175af47485c6-c000.snappy.parquet","partitionValues":{},"size":2914,"modificationTime":1777463358031,"dataChange":true,"stats":"{\"numRecords\":70,\"minValues\":{\"trending_region\":\"AU\",\"category_name\":\"Autos & Vehicles\",\"video_count\":4,\"region_total\":1505,\"pct_of_trending\":0.26578073089701},\"maxValues\":{\"trending_region\":\"US\",\"category_name\":\"Travel & Events\",\"video_count\":599,\"region_total\":1860,\"pct_of_trending\":32.71436373566357},\"nullCount\":{\"trending_region\":0,\"category_name\":0,\"video_count\":0,\"region_total\":0,\"pct_of_trending\":0}}"}}
{"remove":{"path":"part-00000-5f30cae9-ca31-4680-9b95-7c17dde167b3-c000.snappy.parquet","deletionTimestamp":1777463358083,"dataChange":true,"extendedFileMetadata":true,"partitionValues":{},"size":2914}}
