{"commitInfo":{"timestamp":1777461528858,"operation":"WRITE","operationParameters":{"mode":"Overwrite","partitionBy":"[]"},"readVersion":20,"isolationLevel":"Serializable","isBlindAppend":false,"operationMetrics":{"numFiles":"1","numOutputRows":"70","numOutputBytes":"2911"},"engineInfo":"Apache-Spark/3.4.1 Delta-Lake/2.4.0","txnId":"a288794f-5f74-453a-ad86-7d0449794f54"}}
{"add":{"path":"part-00000-5191c843-7589-401d-9da8-ad13f9ab5aae-c000.snappy.parquet","partitionValues":{},"size":2911,"modificationTime":1777461526565,"dataChange":true,"stats":"{\"numRecords\":70,\"minValues\":{\"trending_region\":\"AU\",\"category_name\":\"Autos & Vehicles\",\"video_count\":4,\"region_total\":1496,\"pct_of_trending\":0.267379679144385},\"maxValues\":{\"trending_region\":\"US\",\"category_name\":\"Travel & Events\",\"video_count\":598,\"region_total\":1855,\"pct_of_trending\":32.74917853231106},\"nullCount\":{\"trending_region\":0,\"category_name\":0,\"video_count\":0,\"region_total\":0,\"pct_of_trending\":0}}"}}
{"remove":{"path":"part-00000-e3e90bb8-4103-4cb4-8f6b-32a298aa50fe-c000.snappy.parquet","deletionTimestamp":1777461528857,"dataChange":true,"extendedFileMetadata":true,"partitionValues":{},"size":2912}}
