{"commitInfo":{"timestamp":1777237597603,"operation":"WRITE","operationParameters":{"mode":"Overwrite","partitionBy":"[]"},"readVersion":69,"isolationLevel":"Serializable","isBlindAppend":false,"operationMetrics":{"numFiles":"1","numOutputRows":"14","numOutputBytes":"2965"},"engineInfo":"Apache-Spark/3.4.1 Delta-Lake/2.4.0","txnId":"15a58764-9bca-4730-a5fe-b8388cbd76b0"}}
{"add":{"path":"part-00000-437bf822-b51d-4dcc-93e6-b1bc39f44fef-c000.snappy.parquet","partitionValues":{},"size":2965,"modificationTime":1777237597136,"dataChange":true,"stats":"{\"numRecords\":14,\"minValues\":{\"category_name\":\"Autos & Vehicles\",\"videos\":44,\"total_views\":343832932,\"total_likes\":12813118,\"total_comments\":176316,\"avg_engagement_rate\":0.03367097820035571,\"avg_like_rate\":0.03240828002246097},\"maxValues\":{\"category_name\":\"Travel & Events\",\"videos\":1076,\"total_views\":9179122366,\"total_likes\":360171148,\"total_comments\":6007431,\"avg_engagement_rate\":0.0787414684749924,\"avg_like_rate\":0.0763957136034989},\"nullCount\":{\"category_name\":0,\"videos\":0,\"total_views\":0,\"total_likes\":0,\"total_comments\":0,\"avg_engagement_rate\":0,\"avg_like_rate\":0}}"}}
{"remove":{"path":"part-00000-5a22a5b5-1260-446b-9f20-3d1a7fee8cb5-c000.snappy.parquet","deletionTimestamp":1777237597603,"dataChange":true,"extendedFileMetadata":true,"partitionValues":{},"size":2965}}
